{
    "questions": [
        {
          "question": "Which of these statements is false?",
          "options": [
            "Oranges are colors but not fruits.",
            "Orcas are apex predators.",
            "Oreos are great with milk.",
            "Ottawa is the capital of Canada"
          ],
          "answer": 0
        },
        {
          "question": "How many dogs exist in the world?",
          "options": [
            "-5",
            "0",
            "Dogs don't exist???",
            "At least 3."
          ],
          "answer": 3
        },
        {
          "question": "Solve for x. 2(x + 2)(x + 6) = 32",
          "options": [
            "x = -5",
            "q = 1.4",
            "x = 2",
            "x = square"
          ],
          "answer": 2
        },
        {
          "question": "What song has Taylor Swift released?",
          "options": [
            "Take Me to Church",
            "Yellow Submarine",
            "Teardrops on my Guitar",
            "Maroon 5"
          ],
          "answer": 2
        },
        {
          "question": "What is the capital of Maine?",
          "options": [
            "Portland",
            "Augusta",
            "Newark",
            "Chicago"
          ],
          "answer": 1
        },
        {
          "question": "What vitamin can you take to make falling asleep easier?",
          "options": [
            "Melatonin",
            "Melanin",
            "Gelatin",
            "Vodka"
          ],
          "answer": 0
        },
        {
            "question": "What is the purpose of HTML and CSS?",
            "options": [
                "HTML handles data, CSS handles routing",
                "HTML tells the browser what to display, CSS tells it what style to display it in",
                "HTML runs the database, and CSS is the query language",
                "HTML styles the page, CSS makes it interactive"
            ],
            "answer": 1
        }
      ]
}